product_workflow/__init__.py
product_workflow/admin/__init__.py
product_workflow/admin/product.py
product_workflow/admin/product_workflow.py
product_workflow/admin/step.py
product_workflow/admin/transition.py
product_workflow/admin/workflow.py
product_workflow/apps.py
product_workflow/constants/__init__.py
product_workflow/constants/default_settings.py
product_workflow/constants/types.py
product_workflow/migrations/0001_initial.py
product_workflow/migrations/__init__.py
product_workflow/mixins/__init__.py
product_workflow/mixins/models/__init__.py
product_workflow/mixins/models/timestamp.py
product_workflow/models/__init__.py
product_workflow/models/product.py
product_workflow/models/product_workflow.py
product_workflow/models/step.py
product_workflow/models/transition.py
product_workflow/models/workflow.py
product_workflow/settings/__init__.py
product_workflow/settings/checks.py
product_workflow/settings/conf.py
product_workflow/templates/product_workflow_detail.html
product_workflow/templates/product_workflow_list.html
product_workflow/tests/__init__.py
product_workflow/tests/admin/__init__.py
product_workflow/tests/admin/test_product.py
product_workflow/tests/admin/test_transition.py
product_workflow/tests/conftest.py
product_workflow/tests/constants.py
product_workflow/tests/fixtures/__init__.py
product_workflow/tests/fixtures/admin.py
product_workflow/tests/fixtures/models.py
product_workflow/tests/fixtures/user.py
product_workflow/tests/models/__init__.py
product_workflow/tests/models/test_product.py
product_workflow/tests/models/test_product_workflow.py
product_workflow/tests/models/test_step.py
product_workflow/tests/models/test_transition.py
product_workflow/tests/models/test_workflow.py
product_workflow/tests/settings/__init__.py
product_workflow/tests/settings/test_checks.py
product_workflow/tests/settings/test_conf.py
product_workflow/tests/setup.py
product_workflow/tests/urls.py
product_workflow/tests/validators/__init__.py
dj_product_workflow-1.0.0.dist-info/AUTHORS.md
dj_product_workflow-1.0.0.dist-info/LICENSE
dj_product_workflow-1.0.0.dist-info/METADATA
dj_product_workflow-1.0.0.dist-info/WHEEL
dj_product_workflow-1.0.0.dist-info/RECORD
