Metadata-Version: 2.3
Name: dj-product-workflow
Version: 1.0.0
Summary: A Django package to empower businesses in managing and visualizing product development workflows.
License: MIT
Keywords: django,django product workflow,product,product workflow
Author: ARYAN-NIKNEZHAD
Author-email: aryan513966@gmail.com
Requires-Python: >=3.9
Classifier: Development Status :: 3 - Alpha
Classifier: Environment :: Web Environment
Classifier: Framework :: Django
Classifier: Framework :: Django :: 4.2
Classifier: Framework :: Django :: 5.0
Classifier: Framework :: Django :: 5.1
Classifier: Intended Audience :: Developers
Classifier: License :: OSI Approved :: MIT License
Classifier: Operating System :: OS Independent
Classifier: Programming Language :: Python
Classifier: Programming Language :: Python :: 3 :: Only
Classifier: Programming Language :: Python :: 3.9
Classifier: Programming Language :: Python :: 3.10
Classifier: Programming Language :: Python :: 3.11
Classifier: Programming Language :: Python :: 3.12
Classifier: Programming Language :: Python :: 3.13
Classifier: Topic :: Software Development :: Libraries :: Python Modules
Requires-Dist: django (>=4.2,<5.0) ; python_version == "3.9"
Requires-Dist: django (>=4.2,<5.3) ; python_version >= "3.10"
Project-URL: Changelog, https://github.com/lazarus-org/dj-product-workflow/blob/main/CHANGELOG.md
Project-URL: Issues, https://github.com/lazarus-org/dj-product-workflow/issues
Project-URL: Source Code, https://github.com/Lazarus-org/dj-product-workflow
